[
  {
    "ts": "2026-06-26T15:00:42.573562+00:00",
    "services": {
      "omok": {
        "render": {
          "cpu_peak_m": 0.36843334
        }
      },
      "2048": {
        "render": {
          "cpu_peak_m": 0.42171666
        }
      }
    },
    "aiven": {
      "cpu_pct_avg": 7.590577984327666,
      "cpu_pct_max": 10.616381458747142,
      "mem_pct_avg": 69.84804063237442,
      "mem_pct_max": 71.42651124653375,
      "disk_pct_avg": 0.33521524654659324,
      "disk_pct_max": 0.3352605543817922,
      "load_avg": 0.08462809917355373,
      "load_max": 0.17
    }
  },
  {
    "ts": "2026-06-26T17:00:40.030558+00:00",
    "services": {
      "omok": {
        "render": {
          "cpu_peak_m": 0.35618333
        }
      },
      "2048": {
        "render": {
          "cpu_peak_m": 0.40618333
        }
      }
    },
    "aiven": {
      "cpu_pct_avg": 7.74192620325064,
      "cpu_pct_max": 11.018503083825735,
      "mem_pct_avg": 69.85114622909899,
      "mem_pct_max": 71.64942294301125,
      "disk_pct_avg": 0.3357903075318107,
      "disk_pct_max": 0.33610397716011114,
      "load_avg": 0.24884297520661156,
      "load_max": 0.66
    }
  },
  {
    "ts": "2026-06-26T19:00:39.147047+00:00",
    "services": {
      "omok": {
        "render": {
          "cpu_peak_m": 0.37766667
        }
      },
      "2048": {
        "render": {
          "cpu_peak_m": 0.43025
        }
      }
    },
    "aiven": {
      "cpu_pct_avg": 8.08763315301594,
      "cpu_pct_max": 11.430948419275708,
      "mem_pct_avg": 69.93786116395789,
      "mem_pct_max": 72.10389910052453,
      "disk_pct_avg": 0.3364803807140717,
      "disk_pct_max": 0.3365256885492707,
      "load_avg": 0.1262809917355372,
      "load_max": 0.24
    }
  },
  {
    "ts": "2026-06-26T21:00:38.727638+00:00",
    "services": {
      "omok": {
        "render": {
          "cpu_peak_m": 0.35064999999999996
        }
      },
      "2048": {
        "render": {
          "cpu_peak_m": 0.44623335
        }
      }
    },
    "aiven": {
      "cpu_pct_avg": 7.618282311265166,
      "cpu_pct_max": 10.817107671831465,
      "mem_pct_avg": 69.92194498074446,
      "mem_pct_max": 72.38037552998183,
      "disk_pct_avg": 0.336975281683168,
      "disk_pct_max": 0.3373691113275896,
      "load_avg": 0.0696694214876033,
      "load_max": 0.18
    }
  }
]