[
  {
    "ts": "2026-07-15T15:00:52.254929+00:00",
    "services": {
      "omok": {
        "render": {
          "cpu_peak_m": 0.4777
        }
      },
      "2048": {
        "render": {
          "cpu_peak_m": null
        }
      }
    },
    "aiven": {
      "cpu_pct_avg": 6.779154102761202,
      "cpu_pct_max": 9.095468985017618,
      "mem_pct_avg": 69.59479828893879,
      "mem_pct_max": 72.08453338937028,
      "disk_pct_avg": 0.4056863563714265,
      "disk_pct_max": 0.4056863563714265,
      "load_avg": 0.1003305785123967,
      "load_max": 0.16
    }
  },
  {
    "ts": "2026-07-15T17:00:53.795016+00:00",
    "services": {
      "omok": {
        "render": {
          "cpu_peak_m": null
        }
      },
      "2048": {
        "render": {
          "cpu_peak_m": null
        }
      }
    },
    "aiven": {
      "cpu_pct_avg": 6.652989200457531,
      "cpu_pct_max": 8.859283929806594,
      "mem_pct_avg": 69.74146281846456,
      "mem_pct_max": 72.23987111501172,
      "disk_pct_avg": 0.4056863563714265,
      "disk_pct_max": 0.4056863563714265,
      "load_avg": 0.16363636363636364,
      "load_max": 0.33
    }
  },
  {
    "ts": "2026-07-15T19:00:53.158602+00:00",
    "services": {
      "omok": {
        "render": {
          "cpu_peak_m": null
        }
      },
      "2048": {
        "render": {
          "cpu_peak_m": null
        }
      }
    },
    "aiven": {
      "cpu_pct_avg": 6.61594099151962,
      "cpu_pct_max": 8.333333333658658,
      "mem_pct_avg": 69.75673540761996,
      "mem_pct_max": 72.19207489173743,
      "disk_pct_avg": 0.406108067760586,
      "disk_pct_max": 0.406108067760586,
      "load_avg": 0.1312396694214876,
      "load_max": 0.45
    }
  },
  {
    "ts": "2026-07-15T21:00:53.248482+00:00",
    "services": {
      "omok": {
        "render": {
          "cpu_peak_m": null
        }
      },
      "2048": {
        "render": {
          "cpu_peak_m": null
        }
      }
    },
    "aiven": {
      "cpu_pct_avg": 6.583107511449387,
      "cpu_pct_max": 8.461796246312915,
      "mem_pct_avg": 69.57806824868896,
      "mem_pct_max": 72.21391282133689,
      "disk_pct_avg": 0.406108067760586,
      "disk_pct_max": 0.406108067760586,
      "load_avg": 0.10677685950413224,
      "load_max": 0.19
    }
  },
  {
    "ts": "2026-07-15T23:00:52.649635+00:00",
    "services": {
      "omok": {
        "render": {
          "cpu_peak_m": null
        }
      },
      "2048": {
        "render": {
          "cpu_peak_m": null
        }
      }
    },
    "aiven": {
      "cpu_pct_avg": 6.5433341249777515,
      "cpu_pct_max": 8.800401538857031,
      "mem_pct_avg": 69.06063905757125,
      "mem_pct_max": 71.0025257831782,
      "disk_pct_avg": 0.406108067760586,
      "disk_pct_max": 0.406108067760586,
      "load_avg": 0.05388429752066116,
      "load_max": 0.11
    }
  },
  {
    "ts": "2026-07-16T01:00:52.937628+00:00",
    "services": {
      "omok": {
        "render": {
          "cpu_peak_m": 0.9636
        }
      },
      "2048": {
        "render": {
          "cpu_peak_m": 1.0138834
        }
      }
    },
    "aiven": {
      "cpu_pct_avg": 6.624204532363727,
      "cpu_pct_max": 8.555164908540448,
      "mem_pct_avg": 68.55298636666875,
      "mem_pct_max": 70.05154575458288,
      "disk_pct_avg": 0.406108067760586,
      "disk_pct_max": 0.406108067760586,
      "load_avg": 0.07743801652892562,
      "load_max": 0.17
    }
  },
  {
    "ts": "2026-07-16T03:00:54.402392+00:00",
    "services": {
      "omok": {
        "render": {
          "cpu_peak_m": 0.41963335
        }
      },
      "2048": {
        "render": {
          "cpu_peak_m": 0.65633334
        }
      }
    },
    "aiven": {
      "cpu_pct_avg": 6.746388223884463,
      "cpu_pct_max": 8.465785511216836,
      "mem_pct_avg": 69.07608190970498,
      "mem_pct_max": 70.84553991190661,
      "disk_pct_avg": 0.406951490538905,
      "disk_pct_max": 0.406951490538905,
      "load_avg": 0.23487603305785126,
      "load_max": 0.51
    }
  },
  {
    "ts": "2026-07-16T05:00:49.683557+00:00",
    "services": {
      "omok": {
        "render": {
          "cpu_peak_m": 0.43115
        }
      },
      "2048": {
        "render": {
          "cpu_peak_m": null
        }
      }
    },
    "aiven": {
      "cpu_pct_avg": 6.89793538122768,
      "cpu_pct_max": 8.717434869320257,
      "mem_pct_avg": 69.11141828822574,
      "mem_pct_max": 70.65105872754917,
      "disk_pct_avg": 0.4073732019280645,
      "disk_pct_max": 0.4073732019280645,
      "load_avg": 0.07958677685950413,
      "load_max": 0.15
    }
  },
  {
    "ts": "2026-07-16T07:00:55.403725+00:00",
    "services": {
      "omok": {
        "render": {
          "cpu_peak_m": null
        }
      },
      "2048": {
        "render": {
          "cpu_peak_m": null
        }
      }
    },
    "aiven": {
      "cpu_pct_avg": 7.0487223203426215,
      "cpu_pct_max": 10.55973266478145,
      "mem_pct_avg": 69.18130443030739,
      "mem_pct_max": 70.90569722740702,
      "disk_pct_avg": 0.4077391498277483,
      "disk_pct_max": 0.40779491331722395,
      "load_avg": 0.08223140495867769,
      "load_max": 0.18
    }
  },
  {
    "ts": "2026-07-16T09:00:56.851935+00:00",
    "services": {
      "omok": {
        "render": {
          "cpu_peak_m": null
        }
      },
      "2048": {
        "render": {
          "cpu_peak_m": null
        }
      }
    },
    "aiven": {
      "cpu_pct_avg": 6.652579380897809,
      "cpu_pct_max": 8.644237175118093,
      "mem_pct_avg": 68.74430747014856,
      "mem_pct_max": 70.09151328611397,
      "disk_pct_avg": 0.40779491331722395,
      "disk_pct_max": 0.40779491331722395,
      "load_avg": 0.14090909090909093,
      "load_max": 0.51
    }
  }
]