[
  {
    "ts": "2026-05-25T15:00:25.669458+00:00",
    "services": {
      "omok": {
        "render": {
          "cpu_peak_m": 0.59608335
        }
      },
      "2048": {
        "render": {
          "cpu_peak_m": 0.46866667
        }
      }
    },
    "aiven": {
      "cpu_pct_avg": 7.964730605129184,
      "cpu_pct_max": 10.672853828219417,
      "mem_pct_avg": 65.96034496226955,
      "mem_pct_max": 66.87941392182877,
      "disk_pct_avg": 0.09821344583896154,
      "disk_pct_max": 0.09868046506331997,
      "load_avg": 0.08619834710743801,
      "load_max": 0.18
    }
  },
  {
    "ts": "2026-05-25T15:05:17.107928+00:00",
    "services": {
      "omok": {
        "render": {
          "cpu_peak_m": 0.8041832999999999
        }
      },
      "2048": {
        "render": {
          "cpu_peak_m": 0.46866667
        }
      }
    },
    "aiven": {
      "cpu_pct_avg": 7.884249924546567,
      "cpu_pct_max": 10.911488379744142,
      "mem_pct_avg": 66.0046574224239,
      "mem_pct_max": 66.88353426892681,
      "disk_pct_avg": 0.09828315020080607,
      "disk_pct_max": 0.09868046506331997,
      "load_avg": 0.081900826446281,
      "load_max": 0.16
    }
  },
  {
    "ts": "2026-05-25T15:10:18.482620+00:00",
    "services": {
      "omok": {
        "render": {
          "cpu_peak_m": 0.8041832999999999
        }
      },
      "2048": {
        "render": {
          "cpu_peak_m": 0.45233333
        }
      }
    },
    "aiven": {
      "cpu_pct_avg": 7.819888918992877,
      "cpu_pct_max": 10.911488379744142,
      "mem_pct_avg": 66.02507867990072,
      "mem_pct_max": 66.88353426892681,
      "disk_pct_avg": 0.09835285456265062,
      "disk_pct_max": 0.09868046506331997,
      "load_avg": 0.0793388429752066,
      "load_max": 0.16
    }
  },
  {
    "ts": "2026-05-25T15:15:16.586954+00:00",
    "services": {
      "omok": {
        "render": {
          "cpu_peak_m": 0.8041832999999999
        }
      },
      "2048": {
        "render": {
          "cpu_peak_m": 0.44508334
        }
      }
    },
    "aiven": {
      "cpu_pct_avg": 7.784299652912842,
      "cpu_pct_max": 10.911488379744142,
      "mem_pct_avg": 66.04005494976616,
      "mem_pct_max": 66.93545064236211,
      "disk_pct_avg": 0.09840861805212625,
      "disk_pct_max": 0.09868046506331997,
      "load_avg": 0.08082644628099173,
      "load_max": 0.16
    }
  },
  {
    "ts": "2026-05-25T15:20:16.425912+00:00",
    "services": {
      "omok": {
        "render": {
          "cpu_peak_m": 0.8041832999999999
        }
      },
      "2048": {
        "render": {
          "cpu_peak_m": 0.43616668
        }
      }
    },
    "aiven": {
      "cpu_pct_avg": 7.744136616400346,
      "cpu_pct_max": 10.911488379744142,
      "mem_pct_avg": 65.97167080892085,
      "mem_pct_max": 66.93545064236211,
      "disk_pct_avg": 0.09844347023304853,
      "disk_pct_max": 0.09868046506331997,
      "load_avg": 0.0743801652892562,
      "load_max": 0.16
    }
  },
  {
    "ts": "2026-05-25T15:25:13.463325+00:00",
    "services": {
      "omok": {
        "render": {
          "cpu_peak_m": 0.77748334
        }
      },
      "2048": {
        "render": {
          "cpu_peak_m": 0.43553332
        }
      }
    },
    "aiven": {
      "cpu_pct_avg": 7.586546033968646,
      "cpu_pct_max": 10.911488379744142,
      "mem_pct_avg": 66.00735437688809,
      "mem_pct_max": 67.04216763220134,
      "disk_pct_avg": 0.09848877806824748,
      "disk_pct_max": 0.09910217645247946,
      "load_avg": 0.06892561983471074,
      "load_max": 0.16
    }
  },
  {
    "ts": "2026-05-25T15:30:19.733829+00:00",
    "services": {
      "omok": {
        "render": {
          "cpu_peak_m": 0.812
        }
      },
      "2048": {
        "render": {
          "cpu_peak_m": 0.50436665
        }
      }
    },
    "aiven": {
      "cpu_pct_avg": 7.543451819984295,
      "cpu_pct_max": 10.911488379744142,
      "mem_pct_avg": 66.02562011394087,
      "mem_pct_max": 67.04216763220134,
      "disk_pct_avg": 0.098558482430092,
      "disk_pct_max": 0.09910217645247946,
      "load_avg": 0.06818181818181818,
      "load_max": 0.16
    }
  },
  {
    "ts": "2026-05-25T15:35:14.749009+00:00",
    "services": {
      "omok": {
        "render": {
          "cpu_peak_m": 1.1504167
        }
      },
      "2048": {
        "render": {
          "cpu_peak_m": 0.50436665
        }
      }
    },
    "aiven": {
      "cpu_pct_avg": 7.45910277825944,
      "cpu_pct_max": 10.911488379744142,
      "mem_pct_avg": 66.07871129708595,
      "mem_pct_max": 67.08790348498958,
      "disk_pct_avg": 0.09862818679193656,
      "disk_pct_max": 0.09910217645247946,
      "load_avg": 0.06644628099173555,
      "load_max": 0.16
    }
  },
  {
    "ts": "2026-05-25T15:40:16.091379+00:00",
    "services": {
      "omok": {
        "render": {
          "cpu_peak_m": 1.1504167
        }
      },
      "2048": {
        "render": {
          "cpu_peak_m": 0.50436665
        }
      }
    },
    "aiven": {
      "cpu_pct_avg": 7.436820245635555,
      "cpu_pct_max": 10.911488379744142,
      "mem_pct_avg": 66.0795115297868,
      "mem_pct_max": 67.08790348498958,
      "disk_pct_avg": 0.09869789115378111,
      "disk_pct_max": 0.09910217645247946,
      "load_avg": 0.06884297520661158,
      "load_max": 0.16
    }
  }
]